ucp_cli.py
apis/__init__.py
apis/accounts.py
apis/auth.py
apis/version.py
commands/__init__.py
commands/auth.py
commands/client.py
commands/common.py
commands/config.py
commands/subjects.py
python_ucp_cli-0.1.9.dist-info/LICENSE.txt
python_ucp_cli-0.1.9.dist-info/METADATA
python_ucp_cli-0.1.9.dist-info/WHEEL
python_ucp_cli-0.1.9.dist-info/entry_points.txt
python_ucp_cli-0.1.9.dist-info/top_level.txt
python_ucp_cli-0.1.9.dist-info/RECORD
