Metadata-Version: 2.1
Name: python-ucp-cli
Version: 0.1.9
Summary: UNKNOWN
Home-page: https://github.com/martencassel/python-ucp-cli
Author: Mårten Cassel
Author-email: marten.cassel@conoa.se
License: UNKNOWN
Platform: UNKNOWN
Classifier: Programming Language :: Python :: 3
Classifier: Programming Language :: Python :: 3.7
Classifier: License :: OSI Approved :: GNU Affero General Public License v3
Classifier: Operating System :: OS Independent
Requires-Dist: Click
Requires-Dist: requests
